CHANGELOG
COPYRIGHT
INSTALL
LICENSE
MANIFEST.in
README
setup.py
banknumber/__init__.py
banknumber/tests.py
banknumber.egg-info/PKG-INFO
banknumber.egg-info/SOURCES.txt
banknumber.egg-info/dependency_links.txt
banknumber.egg-info/top_level.txt